db_work_template/__init__.py
db_work_template/db/__init__.py
db_work_template/db/db.py
db_work_template/db/model.py
db_work_template-0.1.0.dist-info/METADATA
db_work_template-0.1.0.dist-info/WHEEL
db_work_template-0.1.0.dist-info/RECORD
