Metadata-Version: 2.3
Name: db-work-template
Version: 0.1.0
Summary: 
Author: rodrigoneal
Author-email: rodrigho2006@gmail.com
Requires-Python: >=3.10
Classifier: Programming Language :: Python :: 3
Classifier: Programming Language :: Python :: 3.10
Classifier: Programming Language :: Python :: 3.11
Classifier: Programming Language :: Python :: 3.12
Classifier: Programming Language :: Python :: 3.13
Requires-Dist: pymysql (>=1.1.1,<2.0.0)
Requires-Dist: python-dotenv (>=1.1.1,<2.0.0)
Requires-Dist: sqlmodel (>=0.0.24,<0.0.25)
